{
  "file": ["ls", "cat", "find", "cp", "mv", "rm", "mkdir", "touch", "cut", "sort", "uniq"],
  "directory": ["ls", "cd", "pwd", "mkdir", "rmdir", "find"],
  "view": ["cat", "less", "head", "tail", "ls", "more", "lsof"],
  "search": ["find", "locate", "grep", "which", "whereis", "pgrep"],
  "copy": ["cp", "scp", "rsync"],
  "move": ["mv"],
  "delete": ["rm", "rmdir"],
  "permission": ["chmod", "chown", "chgrp"],
  "process": ["ps", "top", "kill", "jobs", "pkill", "pgrep", "killall", "htop"],
  "process management": ["ps", "top", "kill", "jobs", "pkill", "pgrep", "killall", "htop"],
  "monitor": ["top", "htop", "lsof", "free", "df", "du"],
  "network": ["ping", "wget", "curl", "ssh", "scp", "netstat", "rsync"],
  "download": ["wget", "curl"],
  "connect": ["ssh", "ping", "telnet"],
  "transfer": ["scp", "rsync"],
  "sync": ["rsync"],
  "system": ["df", "du", "free", "uname", "uptime", "lsof"],
  "disk": ["df", "du"],
  "memory": ["free", "top", "htop"],
  "info": ["uname", "whoami", "which", "whereis", "lsof"],
  "text": ["grep", "sed", "awk", "sort", "wc", "cut", "tr", "uniq"],
  "text processing": ["grep", "sed", "awk", "sort", "wc", "cut", "tr", "uniq"],
  "edit": ["nano", "vim", "sed", "tr"],
  "sort": ["sort", "uniq"],
  "count": ["wc", "du", "df"],
  "compress": ["tar", "gzip", "zip"],
  "compression": ["tar", "gzip", "zip", "gunzip", "unzip"],
  "extract": ["tar", "gunzip", "unzip"],
  "archive": ["tar", "zip", "unzip"],
  "pack": ["tar", "zip"],
  "development": ["npm", "pip", "yarn", "git", "make", "gcc", "node", "python"],
  "compile": ["gcc", "make"],
  "package": ["npm", "pip", "yarn", "composer"],
  "version control": ["git"],
  "container": ["docker", "docker-compose", "kubectl", "podman"],
  "containerization": ["docker", "docker-compose", "kubectl", "podman"],
  "kubernetes": ["kubectl"],
  "terminal": ["tmux", "screen"],
  "session": ["tmux", "screen"],
  "multiplexer": ["tmux", "screen"],
  "advanced tools": ["htop", "tmux", "screen", "rsync", "xargs"],
  "batch": ["xargs"],
  "python": ["pip", "python"],
  "javascript": ["npm", "yarn", "node"],
  "nodejs": ["npm", "yarn", "node"],
  "php": ["composer"],
  "kill": ["kill", "pkill", "killall"],
  "find": ["find", "grep", "pgrep", "which", "whereis"],
  "replace": ["sed", "tr"],
  "transform": ["tr"],
  "unique": ["uniq", "sort"],
  "extract field": ["cut", "awk"],
  "field": ["cut", "awk"],
  "column": ["cut"],
  "delimiter": ["cut", "tr"],
  "backup": ["rsync", "tar", "cp"],
  "remote": ["ssh", "scp", "rsync"],
  "debug": ["lsof", "htop", "ps"],
  "performance": ["top", "htop", "free"],
  "resource": ["top", "htop", "free", "df", "du"],
  "space": ["df", "du"],
  "usage": ["df", "du", "free"]
}